iacs/__init__.py
iacs/csv2md.py
iacs/default_config.py
iacs/find_docs.py
iacs/iacs_cli.py
iacs/transfer_notebooks.py
iacs_cli-0.11.1.dist-info/METADATA
iacs_cli-0.11.1.dist-info/RECORD
iacs_cli-0.11.1.dist-info/WHEEL
iacs_cli-0.11.1.dist-info/entry_points.txt
iacs_cli-0.11.1.dist-info/top_level.txt
