Metadata-Version: 2.1
Name: iacs-cli
Version: 0.11.1
Summary: Command line tool for Harvard IACS course
Home-page: https://github.com/richardskim111/iacs-cli
Author: Richard Kim
Author-email: richardskim111@gmail.com
License: MIT
Platform: UNKNOWN
Requires-Dist: click
Requires-Dist: pelican
Requires-Dist: markdown
Requires-Dist: gitpython
Requires-Dist: beautifulsoup4
